iats
